_memimporter.cp311-win_amd64.pyd
memimport.py
zipextimporter.py
memimport-0.13.0.0.post8.dist-info/LICENSE.txt
memimport-0.13.0.0.post8.dist-info/METADATA
memimport-0.13.0.0.post8.dist-info/MIT-License.txt
memimport-0.13.0.0.post8.dist-info/MPL2-License.txt
memimport-0.13.0.0.post8.dist-info/WHEEL
memimport-0.13.0.0.post8.dist-info/top_level.txt
memimport-0.13.0.0.post8.dist-info/RECORD
