Metadata-Version: 2.1
Name: memimport
Version: 0.13.0.0.post8
Summary: Helps import Python extensions from memory, e.g. extensions from Zip files or Web.
Home-page: http://github.com/SeaHOH/memimport
Author: Thomas Heller <theller@ctypes.org>, Alberto Sottile <alby128@gmail.com>
Maintainer: SeaHOH
Maintainer-email: seahoh@gmail.com
License: MIT/X11 OR (MPL 2.0)
Project-URL: Tracker, http://github.com/SeaHOH/memimport/issues
Keywords: memory importer zip loader
Platform: Windows
Classifier: Development Status :: 4 - Beta
Classifier: Environment :: Console
Classifier: License :: OSI Approved :: MIT License
Classifier: License :: OSI Approved :: Mozilla Public License 2.0 (MPL 2.0)
Classifier: Operating System :: Microsoft :: Windows
Classifier: Programming Language :: C
Classifier: Programming Language :: Python :: 3
Classifier: Programming Language :: Python :: 3.6
Classifier: Programming Language :: Python :: 3.7
Classifier: Programming Language :: Python :: 3.8
Classifier: Programming Language :: Python :: 3.9
Classifier: Programming Language :: Python :: 3.10
Classifier: Programming Language :: Python :: 3.11
Classifier: Programming Language :: Python :: Implementation :: CPython
Classifier: Topic :: Software Development
Classifier: Topic :: Software Development :: Libraries
Classifier: Topic :: Software Development :: Libraries :: Python Modules
Classifier: Topic :: System :: Software Distribution
Classifier: Topic :: Utilities
Requires-Python: >=3.6, <3.12
License-File: LICENSE.txt
License-File: MIT-License.txt
License-File: MPL2-License.txt
